findsylls/__init__.py
findsylls/cli.py
findsylls/audio/__init__.py
findsylls/audio/utils.py
findsylls/config/__init__.py
findsylls/config/constants.py
findsylls/embedding/__init__.py
findsylls/embedding/extractors.py
findsylls/embedding/pipeline.py
findsylls/embedding/pooling.py
findsylls/embedding/storage.py
findsylls/envelope/__init__.py
findsylls/envelope/dispatch.py
findsylls/envelope/gammatone.py
findsylls/envelope/hilbert.py
findsylls/envelope/lowpass.py
findsylls/envelope/rms.py
findsylls/envelope/sbs.py
findsylls/envelope/theta.py
findsylls/evaluation/__init__.py
findsylls/evaluation/boundaries.py
findsylls/evaluation/evaluator.py
findsylls/evaluation/nuclei.py
findsylls/evaluation/spans.py
findsylls/parsing/__init__.py
findsylls/parsing/textgrid_parser.py
findsylls/pipeline/__init__.py
findsylls/pipeline/pipeline.py
findsylls/pipeline/results.py
findsylls/plotting/__init__.py
findsylls/plotting/layers.py
findsylls/plotting/overlays.py
findsylls/plotting/plot_segmentation.py
findsylls/segmentation/__init__.py
findsylls/segmentation/base.py
findsylls/segmentation/dispatch.py
findsylls/segmentation/peakdetect_segmenter.py
findsylls/segmentation/peaks_and_valleys.py
findsylls/segmentation/segment_peakdetect.py
findsylls/segmentation/algorithms/__init__.py
findsylls/segmentation/algorithms/mincut.py
findsylls/segmentation/end2end/__init__.py
findsylls/segmentation/end2end/sylber_segmenter.py
findsylls/segmentation/end2end/vg_hubert_models.py
findsylls/segmentation/end2end/vg_hubert_segmenter.py
findsylls-1.0.1.dist-info/licenses/LICENSE
findsylls-1.0.1.dist-info/METADATA
findsylls-1.0.1.dist-info/WHEEL
findsylls-1.0.1.dist-info/entry_points.txt
findsylls-1.0.1.dist-info/top_level.txt
findsylls-1.0.1.dist-info/RECORD
