Metadata-Version: 2.4
Name: findsylls
Version: 1.0.1
Summary: Unsupervised syllable segmentation, evaluation, and embedding extraction toolkit for speech audio
Author: Héctor Javier
License: MIT License
Project-URL: Homepage, https://github.com/hjvm/findsylls
Project-URL: Issues, https://github.com/hjvm/findsylls/issues
Keywords: speech,syllable,segmentation,audio,phonetics,prosody,unsupervised
Classifier: Programming Language :: Python :: 3
Classifier: License :: OSI Approved :: MIT License
Classifier: Topic :: Scientific/Engineering :: Artificial Intelligence
Classifier: Topic :: Multimedia :: Sound/Audio :: Analysis
Requires-Python: >=3.9
License-File: LICENSE
Requires-Dist: numpy>=1.22
Requires-Dist: scipy>=1.9
Requires-Dist: librosa>=0.10
Requires-Dist: pandas>=1.5
Requires-Dist: soundfile>=0.12
Requires-Dist: matplotlib>=3.7
Requires-Dist: textgrid>=1.5
Requires-Dist: findpeaks>=2.5
Requires-Dist: gammatone>=1.0.0
Requires-Dist: joblib>=1.3
Requires-Dist: tqdm>=4.65
Provides-Extra: viz
Requires-Dist: matplotlib; extra == "viz"
Requires-Dist: seaborn; extra == "viz"
Provides-Extra: end2end
Requires-Dist: sylber>=0.1.2; extra == "end2end"
Provides-Extra: storage
Requires-Dist: h5py>=3.8; extra == "storage"
Provides-Extra: embedding
Requires-Dist: torch>=2.0; extra == "embedding"
Requires-Dist: torchaudio>=2.0; extra == "embedding"
Requires-Dist: transformers>=4.30; extra == "embedding"
Provides-Extra: all
Requires-Dist: matplotlib; extra == "all"
Requires-Dist: seaborn; extra == "all"
Requires-Dist: sylber>=0.1.2; extra == "all"
Requires-Dist: h5py>=3.8; extra == "all"
Requires-Dist: torch>=2.0; extra == "all"
Requires-Dist: torchaudio>=2.0; extra == "all"
Requires-Dist: transformers>=4.30; extra == "all"
Provides-Extra: dev
Requires-Dist: pytest; extra == "dev"
Requires-Dist: pytest-cov; extra == "dev"
Requires-Dist: ruff; extra == "dev"
Requires-Dist: black; extra == "dev"
Requires-Dist: mypy; extra == "dev"
Dynamic: license-file
